LICENSE
systa/__init__.py
systa/backend/__init__.py
systa/backend/access.py
systa/backend/monitors.py
systa/events/__init__.py
systa/events/constants.py
systa/events/decorators/__init__.py
systa/events/decorators/filter_by.py
systa/events/decorators/listen_to.py
systa/events/events.py
systa/events/store.py
systa/events/types.py
systa/exceptions.py
systa/experimental/__init__.py
systa/experimental/decorators/__init__.py
systa/experimental/decorators/dectest.py
systa/experimental/decorators/filter_by.py
systa/experimental/decorators/listen_to.py
systa/experimental/decorators/main.py
systa/experimental/decorators/runner.py
systa/experimental/multi_process.py
systa/scripts/__init__.py
systa/scripts/parse_event_constants_page.py
systa/types.py
systa/utils.py
systa/windows.py
systa-0.2.1.dist-info/LICENSE
systa-0.2.1.dist-info/WHEEL
systa-0.2.1.dist-info/METADATA
systa-0.2.1.dist-info/RECORD
