Metadata-Version: 2.1
Name: systa
Version: 0.2.1
Summary: Windows GUI automation with a cool API.
Home-page: https://github.com/dmwyatt/systa
License: MIT
Keywords: automation,windows
Author: Dustin Wyatt
Author-email: dustin.wyatt@gmail.com
Requires-Python: >=3.8,<4.0
Classifier: Development Status :: 3 - Alpha
Classifier: Environment :: Win32 (MS Windows)
Classifier: Intended Audience :: Developers
Classifier: Intended Audience :: System Administrators
Classifier: License :: OSI Approved :: MIT License
Classifier: Operating System :: Microsoft :: Windows
Classifier: Programming Language :: Python :: 3
Classifier: Programming Language :: Python :: 3.10
Classifier: Programming Language :: Python :: 3.8
Classifier: Programming Language :: Python :: 3.9
Classifier: Topic :: Desktop Environment :: Window Managers
Classifier: Topic :: Software Development :: Quality Assurance
Classifier: Topic :: Software Development :: Testing
Classifier: Topic :: System :: Monitoring
Classifier: Topic :: System :: Systems Administration
Requires-Dist: boltons (>=21.0.0,<22.0.0)
Requires-Dist: pynput (>=1.7.3,<2.0.0)
Requires-Dist: pywin32 (>=301)
Requires-Dist: typeguard (>=2.12.0,<3.0.0)
Requires-Dist: typing-inspect (>=0.7.1,<0.8.0)
Project-URL: Documentation, https://dmwyatt.github.io/systa/
Project-URL: Repository, https://github.com/dmwyatt/systa
